fds/__init__.py
fds/sdk/__init__.py
fds/sdk/IRNNotes/__init__.py
fds/sdk/IRNNotes/api_client.py
fds/sdk/IRNNotes/configuration.py
fds/sdk/IRNNotes/exceptions.py
fds/sdk/IRNNotes/model_utils.py
fds/sdk/IRNNotes/rest.py
fds/sdk/IRNNotes/api/__init__.py
fds/sdk/IRNNotes/api/attachments_api.py
fds/sdk/IRNNotes/api/comments_api.py
fds/sdk/IRNNotes/api/events_api.py
fds/sdk/IRNNotes/api/identifiers_api.py
fds/sdk/IRNNotes/api/notes_api.py
fds/sdk/IRNNotes/apis/__init__.py
fds/sdk/IRNNotes/model/__init__.py
fds/sdk/IRNNotes/model/attachment_summary_dto.py
fds/sdk/IRNNotes/model/comment_dto.py
fds/sdk/IRNNotes/model/comment_summary_dto.py
fds/sdk/IRNNotes/model/create_body_dto.py
fds/sdk/IRNNotes/model/create_comment_dto.py
fds/sdk/IRNNotes/model/create_custom_field_value_dto.py
fds/sdk/IRNNotes/model/create_note_dto.py
fds/sdk/IRNNotes/model/custom_field_value_dto.py
fds/sdk/IRNNotes/model/event_snippet_dto.py
fds/sdk/IRNNotes/model/new_item_dto.py
fds/sdk/IRNNotes/model/note_dto.py
fds/sdk/IRNNotes/model/note_event_dto.py
fds/sdk/IRNNotes/model/note_summary_dto.py
fds/sdk/IRNNotes/model/operation.py
fds/sdk/IRNNotes/model/operation_type.py
fds/sdk/IRNNotes/model/problem_details.py
fds/sdk/IRNNotes/model/record_change_dto.py
fds/sdk/IRNNotes/model/record_event_summary_dto.py
fds/sdk/IRNNotes/model/related_records_dto.py
fds/sdk/IRNNotes/model/subcomment_summary_dto.py
fds/sdk/IRNNotes/model/update_note_dto.py
fds/sdk/IRNNotes/model/user_serial_dto.py
fds/sdk/IRNNotes/model/user_team_lookup_dto.py
fds/sdk/IRNNotes/models/__init__.py
fds.sdk.IRNNotes-4.0.2.dist-info/LICENSE
fds.sdk.IRNNotes-4.0.2.dist-info/METADATA
fds.sdk.IRNNotes-4.0.2.dist-info/WHEEL
fds.sdk.IRNNotes-4.0.2.dist-info/top_level.txt
fds.sdk.IRNNotes-4.0.2.dist-info/RECORD
